slickconf/__init__.py
slickconf/builder.py
slickconf/config.py
slickconf/constants.py
slickconf/container.py
slickconf/evaluate.py
slickconf/hooks.py
slickconf/imports.py
slickconf/lambda_finder.py
slickconf/loader.py
slickconf/patch.py
slickconf/patch_fn.py
slickconf/pyconfig.py
slickconf/selector.py
slickconf/summarize.py
slickconf/test.py
slickconf/tree.py
slickconf-0.1.16.dist-info/licenses/LICENSE
slickconf-0.1.16.dist-info/METADATA
slickconf-0.1.16.dist-info/WHEEL
slickconf-0.1.16.dist-info/top_level.txt
slickconf-0.1.16.dist-info/RECORD
