Metadata-Version: 2.4
Name: slickconf
Version: 0.1.16
Summary: Configuration library for machine learning projects
Author-email: Kim Seonghyeon <kim.seonghyeon@outlook.com>
License: MIT License
Requires-Python: >=3.9
License-File: LICENSE
Requires-Dist: pydantic
Requires-Dist: libcst
Dynamic: license-file
